LICENSE.txt
MANIFEST.in
README.rst
setup.py
files/__init__.py
matematyka.py.egg-info/SOURCES.txt
matematyka.py.egg-info/dependency_links.txt
matematyka.py.egg-info/top_level.txt
matematykab.egg-info/PKG-INFO
matematykab.egg-info/SOURCES.txt
matematykab.egg-info/dependency_links.txt
matematykab.egg-info/top_level.txt